abtestools/.DS_Store
abtestools/__init__.py
abtestools/_utils/log/__init__.py
abtestools/_utils/log/log.py
abtestools/audiences/__init__.py
abtestools/audiences/_audiences.py
abtestools/campaign/__init__.py
abtestools/campaign/campaign.py
abtestools/test/__init__.py
abtestools/test/abtest.py
abtestools-1.1.4.dist-info/LICENSE
abtestools-1.1.4.dist-info/METADATA
abtestools-1.1.4.dist-info/WHEEL
abtestools-1.1.4.dist-info/RECORD
