Metadata-Version: 2.1
Name: abtestools
Version: 1.1.4
Summary: AB Test Framework for Python
License: MIT
Author: Pablo Minué
Requires-Python: >=3.10,<4.0
Classifier: License :: OSI Approved :: MIT License
Classifier: Programming Language :: Python :: 3
Classifier: Programming Language :: Python :: 3.10
Classifier: Programming Language :: Python :: 3.11
Classifier: Programming Language :: Python :: 3.12
Requires-Dist: pandas (>=2.2.3,<3.0.0)
Requires-Dist: pydantic (>=2.9.2,<3.0.0)
Requires-Dist: rich (>=13.9.2,<14.0.0)
Requires-Dist: scipy (>=1.14.1,<2.0.0)
Requires-Dist: uuid (>=1.30,<2.0)
